<keymap version="1" name="marlon keymap" parent="Mac OS X 10.5+">
  <action id="ActivateFavoritesToolWindow" />
  <action id="ActivateTODOToolWindow">
    <keyboard-shortcut first-keystroke="meta 2" />
  </action>
  <action id="ActivateTerminalToolWindow">
    <keyboard-shortcut first-keystroke="ctrl back_quote" />
  </action>
  <action id="AddToFavoritesPopup" />
  <action id="Back">
    <keyboard-shortcut first-keystroke="meta minus" />
  </action>
  <action id="CollapseAll">
    <keyboard-shortcut first-keystroke="meta subtract" />
  </action>
  <action id="CollapseExpandableComponent">
    <keyboard-shortcut first-keystroke="shift enter" />
    <keyboard-shortcut first-keystroke="meta subtract" />
  </action>
  <action id="CollapseRegion">
    <keyboard-shortcut first-keystroke="meta open_bracket" />
  </action>
  <action id="CollapseRegionRecursively" />
  <action id="DuplicatesForm.SendToRight" />
  <action id="ExpandAll" />
  <action id="ExpandExpandableComponent">
    <keyboard-shortcut first-keystroke="shift enter" />
  </action>
  <action id="ExpandRegion">
    <keyboard-shortcut first-keystroke="meta close_bracket" />
  </action>
  <action id="ExpandRegionRecursively" />
  <action id="FileChooser.GotoProject" />
  <action id="FileChooser.TogglePathShowing" />
  <action id="FileStructurePopup">
    <keyboard-shortcut first-keystroke="meta r" />
  </action>
  <action id="Forward">
    <keyboard-shortcut first-keystroke="meta equals" />
  </action>
  <action id="GotoFile">
    <keyboard-shortcut first-keystroke="meta p" />
  </action>
  <action id="Images.Editor.ZoomIn" />
  <action id="Images.Editor.ZoomOut">
    <keyboard-shortcut first-keystroke="meta subtract" />
  </action>
  <action id="ParameterInfo" />
  <action id="QuickChangeScheme" />
  <action id="ReformatCode">
    <keyboard-shortcut first-keystroke="shift alt f" />
  </action>
  <action id="Refresh" />
  <action id="Replace" />
  <action id="Rerun" />
  <action id="UML.ZoomIn" />
  <action id="UML.ZoomOut">
    <keyboard-shortcut first-keystroke="meta subtract" />
  </action>
  <action id="Vcs.Log.Refresh" />
  <action id="hg4idea.QRefresh" />
</keymap>